example/__init__.py
example/conf.py
example/main.py
example/permissions.py
example/pure_flask_example.py
example/rate_limit_load.py
example/redis_repository.py
example/models/__init__.py
example/routes/__init__.py
example/routes/api_some.py
example/sockets/__init__.py
example/sockets/on_connect.py
example/sockets/on_disconnect.py
example/sockets/on_json.py
example/sockets/on_message.py
example/sockets/on_open.py
example/workers/__init__.py
example/workers/worker.py
ul_api_utils/__init__.py
ul_api_utils/conf.py
ul_api_utils/const.py
ul_api_utils/errors.py
ul_api_utils/main.py
ul_api_utils/py.typed
ul_api_utils/sentry.py
ul_api_utils/access/__init__.py
ul_api_utils/api_resource/__init__.py
ul_api_utils/api_resource/api_request.py
ul_api_utils/api_resource/api_resource.py
ul_api_utils/api_resource/api_resource_config.py
ul_api_utils/api_resource/api_resource_error_handling.py
ul_api_utils/api_resource/api_resource_fn_typing.py
ul_api_utils/api_resource/api_resource_type.py
ul_api_utils/api_resource/api_response.py
ul_api_utils/api_resource/api_response_db.py
ul_api_utils/api_resource/api_response_payload_alias.py
ul_api_utils/api_resource/db_types.py
ul_api_utils/api_resource/signature_check.py
ul_api_utils/commands/__init__.py
ul_api_utils/commands/cmd_enc_keys.py
ul_api_utils/commands/cmd_gen_api_user_token.py
ul_api_utils/commands/cmd_gen_new_api_user.py
ul_api_utils/commands/cmd_generate_api_docs.py
ul_api_utils/commands/cmd_start.py
ul_api_utils/commands/cmd_worker_start.py
ul_api_utils/commands/start/__init__.py
ul_api_utils/commands/start/gunicorn.conf.local.py
ul_api_utils/commands/start/gunicorn.conf.py
ul_api_utils/commands/start/wsgi.py
ul_api_utils/conf/ul-debugger-main.js
ul_api_utils/conf/ul-debugger-ui.js
ul_api_utils/debug/__init__.py
ul_api_utils/debug/debugger.py
ul_api_utils/debug/malloc.py
ul_api_utils/debug/stat.py
ul_api_utils/encrypt/__init__.py
ul_api_utils/encrypt/encrypt_decrypt_abstract.py
ul_api_utils/encrypt/encrypt_decrypt_aes_xtea.py
ul_api_utils-9.3.2.dist-info/LICENSE
ul_api_utils-9.3.2.dist-info/METADATA
ul_api_utils-9.3.2.dist-info/WHEEL
ul_api_utils-9.3.2.dist-info/entry_points.txt
ul_api_utils-9.3.2.dist-info/top_level.txt
ul_api_utils-9.3.2.dist-info/RECORD
