Metadata-Version: 2.1
Name: ul-api-utils
Version: 9.3.2
Summary: Python api utils
Author: Unic-lab
Author-email: 
License: MIT
Platform: any
Classifier: Intended Audience :: Developers
Classifier: License :: OSI Approved :: MIT License
Classifier: Programming Language :: Python
Classifier: Programming Language :: Python :: 3.8
Classifier: Programming Language :: Python :: 3.9
Classifier: Programming Language :: Python :: 3.10
Classifier: Operating System :: OS Independent
License-File: LICENSE
Requires-Dist: ul-unipipeline (==2.0.6)
Requires-Dist: jinja2 (==3.1.6)
Requires-Dist: flask (==3.1.0)
Requires-Dist: flask-wtf (==1.2.2)
Requires-Dist: flask-limiter (==3.10.1)
Requires-Dist: flask-caching (==2.3.1)
Requires-Dist: flask-swagger-ui (==4.11.1)
Requires-Dist: flask-monitoringdashboard (==3.3.2)
Requires-Dist: pycryptodome (==3.21.0)
Requires-Dist: pyjwt (==2.10.1)
Requires-Dist: gunicorn (==23.0.0)
Requires-Dist: gevent (==24.11.1)
Requires-Dist: gevent-websocket (==0.10.1)
Requires-Dist: pyyaml (==6.0)
Requires-Dist: requests (==2.32.0)
Requires-Dist: cryptography (==44.0.2)
Requires-Dist: colored (==1.4.3)
Requires-Dist: flask-socketio (==5.5.1)
Requires-Dist: ormsgpack (==1.8.0)
Requires-Dist: msgpack (==1.1.0)
Requires-Dist: msgpack-types (==0.5.0)
Requires-Dist: fastavro (==1.10.0)
Requires-Dist: factory-boy (==3.3.0)
Requires-Dist: sentry-sdk[flask] (==2.22.0)
Requires-Dist: faker (==37.0.0)
Requires-Dist: types-requests (==2.32.0.20250306)
Requires-Dist: types-jinja2 (==2.11.9)
Requires-Dist: xlsxwriter (==3.2.2)
Requires-Dist: werkzeug (==3.1.3)
Requires-Dist: frozendict (==2.4.4)
Requires-Dist: wtforms (==3.0.1)
Requires-Dist: wtforms-alchemy (==0.18.0)
Requires-Dist: pathvalidate (==3.2.3)
